master.v
// Code for Master Dual Data Link (D2L)

module master (
    input clk, rstn,
    input out_en,
    output sclk, // slave clock generated by master to communicate
    output reg DL0, DL1,
    output reg CS
);

    
    reg [7:0]  data_in = 8'b0011_1010;

    reg [3:0] state, next_state;
    reg [2:0] count;

    reg slave_clk = 1'b0;
    reg [1:0] data_cycle;

    localparam IDLE = 0;
    localparam START_TX = 1;
    localparam DATA_TX = 2;
    localparam END_TX = 3;

    always @(posedge clk or negedge rstn) begin
        if (!rstn)
            state <= IDLE;
        else
            state <= next_state;
    end

    // Slave clock generator

    always @(posedge clk or negedge rstn) begin

        if(!rstn) begin
            slave_clk <= 1'b0;
        end
        else begin
            case (state)

                IDLE: begin
                    if(out_en)
                        slave_clk <= 1'b1;
                    else
                        slave_clk <= 1'b0;
                end

                START_TX, DATA_TX: begin
                    slave_clk <= (count == 3'd3 || count == 3'd7)? ~slave_clk : slave_clk; 
                end
                
                END_TX: begin
                    if (count < 3'd3)
                        slave_clk <= 1'b1;
                    else
                        slave_clk <= 1'b0;
                end

                default:
                    slave_clk <= 1'b0;
            endcase
        end
    end

    assign sclk = slave_clk;

    // Counter logic
    always @(posedge clk or negedge rstn) begin

        if (!rstn) begin
            count <= 1'd0;
            data_cycle <= 2'd0;
        end

        else begin
            case (state)

                IDLE: begin
                    count <= 3'd0;
                end

                START_TX, END_TX: begin
                    data_cycle <= 2'd0;
                    if (count < 3'd7)
                        count <= count + 1'd1;
                    else
                        count <= 3'd0;
                end

                DATA_TX : begin
                    if (count == 3'd7) begin
                        count <= 3'd0;
                        data_cycle <= data_cycle + 1'd1;
                    end else begin
                        count <= count + 1'd1;
                    end
                end

                default: begin
                    count <= 3'd0;
                    data_cycle <= 2'd0;
                end

            endcase
        end
    end

    // state trans
    always @(*) begin

        case(state)

            IDLE: begin
                DL0 = 4'd0;
                DL1 = 4'd0;
                CS  = 1'd1;
                if (out_en)
                    next_state = START_TX;
                else
                    next_state = IDLE;
            end

            START_TX: begin
                DL0 = 4'd0;
                DL1 = 4'd0;
                CS  = 1'd0;
                if(count == 3'd7)
                    next_state = DATA_TX;
                else
                    next_state = START_TX;
            end

            DATA_TX: begin
                // Data is passed from LSB to MSB
                DL0 = data_in [3 - data_cycle];
                DL1 = data_in [7 - data_cycle];
                if(data_cycle == 2'd3 && count == 3'd7)
                    next_state = END_TX;
                else
                    next_state = DATA_TX;
            end

            END_TX: begin
                DL0 = 4'd0;
                DL1 = 4'd0;
                CS  = 1'd1;
                if(count == 3'd7)
                    next_state = IDLE;
                else
                    next_state = END_TX;
            end

            default: begin
                next_state = IDLE;
            end
        endcase
    end

endmodule //master

master_tb.v
`timescale 1ns/1ps

module tb_master;

    // DUT signals
    reg  clk;
    reg  rstn;
    reg  out_en;
    wire sclk;
    wire DL0;
    wire DL1;
    wire CS;

    // Instantiate DUT
    master dut (
        .clk   (clk),
        .rstn  (rstn),
        .out_en(out_en),
        .sclk  (sclk),
        .DL0   (DL0),
        .DL1   (DL1),
        .CS    (CS)
    );

    // -------------------------------------------------
    // Clock generation: 100 MHz (10 ns period)
    // -------------------------------------------------
    initial clk = 1'b0;
    always #5 clk = ~clk;

    // -------------------------------------------------
    // Stimulus
    // -------------------------------------------------
    initial begin
        // Init
        rstn   = 1'b0;
        out_en = 1'b0;

        // Hold reset
        #30;
        rstn = 1'b1;
        #40;

        out_en = 1'b1;
        #20;
        out_en = 1'b0;
        #500;

        

        // // Wait few clocks
        // #40;

        // // Trigger transmission
        // out_en = 1'b1;
        // #10;
        // out_en = 1'b0;

        // // Let transaction complete
        // #500;

        // // Trigger again
        // out_en = 1'b1;
        // #10;
        // out_en = 1'b0;

        // #500;
        $finish;
    end

    // -------------------------------------------------
    // Optional monitor (console)
    // -------------------------------------------------
    initial begin
        $display("Time\tCS\tSCLK\tDL0\tDL1\tSTATE");
        $monitor("%0t\t%b\t%b\t%b\t%b\t%0d",
                 $time, CS, sclk, DL0, DL1, dut.state);
    end

    // -------------------------------------------------
    // Dump waves (for GTKWave / Vivado)
    // -------------------------------------------------
    initial begin
        $dumpfile("master_tb.vcd");
        $dumpvars(0, tb_master);
    end

endmodule

master_tb.vcd
$date
	Sat Dec 27 16:24:28 2025
$end
$version
	Icarus Verilog
$end
$timescale
	1ps
$end
$scope module tb_master $end
$var wire 1 ! sclk $end
$var wire 1 " DL1 $end
$var wire 1 # DL0 $end
$var wire 1 $ CS $end
$var reg 1 % clk $end
$var reg 1 & out_en $end
$var reg 1 ' rstn $end
$scope module dut $end
$var wire 1 % clk $end
$var wire 1 & out_en $end
$var wire 1 ' rstn $end
$var wire 1 ! sclk $end
$var reg 1 $ CS $end
$var reg 1 # DL0 $end
$var reg 1 " DL1 $end
$var reg 3 ( count [2:0] $end
$var reg 2 ) data_cycle [1:0] $end
$var reg 8 * data_in [7:0] $end
$var reg 4 + next_state [3:0] $end
$var reg 1 , slave_clk $end
$var reg 4 - state [3:0] $end
$upscope $end
$upscope $end
$enddefinitions $end
#0
$dumpvars
b0 -
0,
b0 +
b111010 *
b0 )
b0 (
0'
0&
0%
1$
0#
0"
0!
$end
#5000
1%
#10000
0%
#15000
1%
#20000
0%
#25000
1%
#30000
0%
1'
#35000
1%
#40000
0%
#45000
1%
#50000
0%
#55000
1%
#60000
0%
#65000
1%
#70000
b1 +
0%
1&
#75000
0$
b1 -
1!
1,
1%
#80000
0%
#85000
b1 (
1%
#90000
0%
0&
#95000
b10 (
1%
#100000
0%
#105000
b11 (
1%
#110000
0%
#115000
0!
0,
b100 (
1%
#120000
0%
#125000
b101 (
1%
#130000
0%
#135000
b110 (
1%
#140000
0%
#145000
b10 +
b111 (
1%
#150000
0%
#155000
1#
b10 -
1!
1,
b0 (
1%
#160000
0%
#165000
b1 (
1%
#170000
0%
#175000
b10 (
1%
#180000
0%
#185000
b11 (
1%
#190000
0%
#195000
0!
0,
b100 (
1%
#200000
0%
#205000
b101 (
1%
#210000
0%
#215000
b110 (
1%
#220000
0%
#225000
b111 (
1%
#230000
0%
#235000
0#
1!
1,
b1 )
b0 (
1%
#240000
0%
#245000
b1 (
1%
#250000
0%
#255000
b10 (
1%
#260000
0%
#265000
b11 (
1%
#270000
0%
#275000
0!
0,
b100 (
1%
#280000
0%
#285000
b101 (
1%
#290000
0%
#295000
b110 (
1%
#300000
0%
#305000
b111 (
1%
#310000
0%
#315000
1"
1#
1!
1,
b10 )
b0 (
1%
#320000
0%
#325000
b1 (
1%
#330000
0%
#335000
b10 (
1%
#340000
0%
#345000
b11 (
1%
#350000
0%
#355000
0!
0,
b100 (
1%
#360000
0%
#365000
b101 (
1%
#370000
0%
#375000
b110 (
1%
#380000
0%
#385000
b111 (
1%
#390000
0%
#395000
0#
1!
1,
b11 )
b0 (
1%
#400000
0%
#405000
b1 (
1%
#410000
0%
#415000
b10 (
1%
#420000
0%
#425000
b11 (
1%
#430000
0%
#435000
0!
0,
b100 (
1%
#440000
0%
#445000
b101 (
1%
#450000
0%
#455000
b110 (
1%
#460000
0%
#465000
b11 +
b111 (
1%
#470000
0%
#475000
1$
0"
b11 -
1!
1,
b0 )
b0 (
1%
#480000
0%
#485000
b1 (
1%
#490000
0%
#495000
b10 (
1%
#500000
0%
#505000
b11 (
1%
#510000
0%
#515000
0!
0,
b100 (
1%
#520000
0%
#525000
b101 (
1%
#530000
0%
#535000
b110 (
1%
#540000
0%
#545000
b0 +
b111 (
1%
#550000
0%
#555000
b0 -
b0 (
1%
