master.v
// Code for Master Dual Data Link (D2L)

module master (
    input clk, rstn,
    input out_en,
    input [70:0] data,
    output sclk, // slave clock generated by master to communicate
    output DataLine0, DataLine1,
    output reg CS // CS == 0 selecting the slave device, CS == 1 by default
);

    reg DL0, DL1;
    reg [6:0]  d_width;
    reg [63:0] shreg;

    reg [3:0] state, next_state;
    reg [2:0] count;

    reg slave_clk = 1'b0;
    reg [5:0] data_cycle;

    localparam IDLE = 0;
    localparam START_TX = 1;
    localparam DATA_TX = 2;
    localparam END_TX = 3;

    always @(posedge clk or negedge rstn) begin
        if (!rstn)
            state <= IDLE;
        else
            state <= next_state;
    end

    // Slave clock generator
    always @(posedge clk or negedge rstn) begin

        if(!rstn) begin
            slave_clk <= 1'b0;
        end
        else begin
            case (state)

                IDLE: begin
                    if(out_en)
                        slave_clk <= 1'b1;
                    else
                        slave_clk <= 1'b0;
                end

                START_TX, DATA_TX: begin
                    slave_clk <= (count == 3'd3 || count == 3'd7)? ~slave_clk : slave_clk; 
                end
                
                END_TX: begin
                    if (count < 3'd3)
                        slave_clk <= 1'b1;
                    else
                        slave_clk <= 1'b0;
                end

                default:
                    slave_clk <= 1'b0;
            endcase
        end
    end

    assign sclk = slave_clk;

    // Counter logic
    always @(posedge clk or negedge rstn) begin

        if (!rstn) begin
            count <= 1'd0;
            data_cycle <= 5'd0;
        end

        else begin
            case (state)

                IDLE: begin
                    count <= 3'd0;
                end

                START_TX: begin
                    data_cycle <= 5'd0;
                    if (count == 3'd0) begin
                        d_width <= data[70:64];
                        shreg   <= data[63:0];
                        count <= count + 1'd1;
                    end
                    else if (count < 3'd7)
                        count <= count + 1'd1;
                    else
                        count <= 3'd0;
                end


                DATA_TX : begin
                    if (count == 3'd7) begin
                        count <= 3'd0;
                        shreg <= shreg >> 2;
                        if (data_cycle < (d_width >> 1) - 1)
                            data_cycle <= data_cycle + 1'd1;
                    end else begin
                        count <= count + 1'd1;
                    end
                end

                END_TX: begin
                    data_cycle <= 5'd0;
                    d_width <= 0;
                    shreg <= 0;
                    if (count < 3'd7)
                        count <= count + 1'd1;
                    else
                        count <= 3'd0;
                end

                default: begin
                    count <= 3'd0;
                    data_cycle <= 5'd0;
                end

            endcase
        end
    end

    // state trans
    always @(*) begin
        
        next_state = state;
        DL0 = 1'b0;
        DL1 = 1'b0;
        CS  = 1'b1;

        case(state)

            IDLE: begin
                DL0 = 1'd0;
                DL1 = 1'd0;
                CS  = 1'd1;
                if (out_en)
                    next_state = START_TX;
                else
                    next_state = IDLE;
            end

            START_TX: begin
                DL0 = 1'd0;
                DL1 = 1'd0;
                CS  = 1'd0;
                if(count == 3'd7)
                    next_state = DATA_TX;
                else
                    next_state = START_TX;
            end

            DATA_TX: begin
                // Data is passed from LSB to MSB
                DL0 = shreg[0]; //Lower half bits
                DL1 = shreg[1]; //Upper half bits
                if(data_cycle == (d_width >> 1) - 1 && count == 3'd7)
                    next_state = END_TX;
                else
                    next_state = DATA_TX;
            end

            END_TX: begin
                DL0 = 1'd0;
                DL1 = 1'd0;
                CS  = 1'd1;
                if(count == 3'd7)
                    next_state = IDLE;
                else
                    next_state = END_TX;
            end

            default: begin
                next_state = IDLE;
            end
        endcase
    end

    assign DataLine0 = DL0;
    assign DataLine1 = DL1;

endmodule //master

sim/tb/master_tb.v
`timescale 1ns/1ps

module tb_master;

    // DUT signals
    reg  clk;
    reg  rstn;
    reg  out_en;
    reg [70:0] data;
    wire sclk;
    wire DataLine0;
    wire DataLine1;
    wire CS;

    // Instantiate DUT
    master dut (
        .clk   (clk),
        .rstn  (rstn),
        .out_en(out_en),
        .data(data),
        .sclk  (sclk),
        .DataLine0   (DataLine0),
        .DataLine1   (DataLine1),
        .CS    (CS)
    );

    // -------------------------------------------------
    // Clock generation: 100 MHz (10 ns period)
    // -------------------------------------------------
    initial clk = 1'b0;
    always #5 clk = ~clk;

    // -------------------------------------------------
    // Stimulus
    // -------------------------------------------------
    initial begin

        // data = {7'd8, 56'd95, 8'b0101_1010};
        // data = {7'd16, 48'd0, 16'b1010_1100_0110_1001};
        // data = {7'd24, 40'd0, 24'b11001010_01101100_10101010};
        // data = {7'd32, 32'd0, 32'hA5C3_7F2E};
        // data = {7'd48, 16'd0, 48'h1234_5678_ABCD};
        // data = {7'd64, 64'hFEDC_BA98_7654_3210};



        // Init
        rstn   = 1'b0;
        out_en = 1'b0;

        // Hold reset
        #30;
        rstn = 1'b1;
        #40;

        out_en = 1'b1;
        #20;
        out_en = 1'b0;
        #4000;
        // if (CS == 1)
        $finish;
    end

    // -------------------------------------------------
    // Optional monitor (console)
    // -------------------------------------------------
    initial begin
        $display("Time\tCS\tSCLK\tDL0\tDL1\tSTATE");
    end
    always @(posedge sclk)
        $display("%0t\t%b\t%b\t%b\t%b\t%0d",
                 $time, CS, sclk, DataLine0, DataLine1, dut.state);
    // -------------------------------------------------
    // Dump waves (for GTKWave / Vivado)
    // -------------------------------------------------
    initial begin
        $dumpfile("master_tb.vcd");
        $dumpvars(0, tb_master);
    end

endmodule

master_tb.vcd
$date
	Mon Dec 29 12:34:32 2025
$end
$version
	Icarus Verilog
$end
$timescale
	1ps
$end
$scope module tb_master $end
$var wire 1 ! sclk $end
$var wire 1 " DataLine1 $end
$var wire 1 # DataLine0 $end
$var wire 1 $ CS $end
$var reg 1 % clk $end
$var reg 71 & data [70:0] $end
$var reg 1 ' out_en $end
$var reg 1 ( rstn $end
$scope module dut $end
$var wire 1 # DataLine0 $end
$var wire 1 " DataLine1 $end
$var wire 1 % clk $end
$var wire 71 ) data [70:0] $end
$var wire 1 ' out_en $end
$var wire 1 ( rstn $end
$var wire 1 ! sclk $end
$var reg 1 $ CS $end
$var reg 1 * DL0 $end
$var reg 1 + DL1 $end
$var reg 3 , count [2:0] $end
$var reg 7 - d_width [6:0] $end
$var reg 6 . data_cycle [5:0] $end
$var reg 4 / next_state [3:0] $end
$var reg 64 0 shreg [63:0] $end
$var reg 1 1 slave_clk $end
$var reg 4 2 state [3:0] $end
$upscope $end
$upscope $end
$enddefinitions $end
#0
$dumpvars
b0 2
01
bx 0
b0 /
b0 .
bx -
b0 ,
0+
0*
b10000001111111011011100101110101001100001110110010101000011001000010000 )
0(
0'
b10000001111111011011100101110101001100001110110010101000011001000010000 &
0%
1$
0#
0"
0!
$end
#5000
1%
#10000
0%
#15000
1%
#20000
0%
#25000
1%
#30000
0%
1(
#35000
1%
#40000
0%
#45000
1%
#50000
0%
#55000
1%
#60000
0%
#65000
1%
#70000
b1 /
0%
1'
#75000
0$
b1 2
1!
11
1%
#80000
0%
#85000
0$
b1 ,
b1111111011011100101110101001100001110110010101000011001000010000 0
b1000000 -
1%
#90000
0$
0%
0'
#95000
0$
b10 ,
1%
#100000
0%
#105000
0$
b11 ,
1%
#110000
0%
#115000
0$
0!
01
b100 ,
1%
#120000
0%
#125000
0$
b101 ,
1%
#130000
0%
#135000
0$
b110 ,
1%
#140000
0%
#145000
b10 /
0$
b111 ,
1%
#150000
0%
#155000
1$
b10 2
1!
11
b0 ,
1%
#160000
0%
#165000
b1 ,
1%
#170000
0%
#175000
b10 ,
1%
#180000
0%
#185000
b11 ,
1%
#190000
0%
#195000
0!
01
b100 ,
1%
#200000
0%
#205000
b101 ,
1%
#210000
0%
#215000
b110 ,
1%
#220000
0%
#225000
b111 ,
1%
#230000
0%
#235000
1!
11
b1 .
b11111110110111001011101010011000011101100101010000110010000100 0
b0 ,
1%
#240000
0%
#245000
b1 ,
1%
#250000
0%
#255000
b10 ,
1%
#260000
0%
#265000
b11 ,
1%
#270000
0%
#275000
0!
01
b100 ,
1%
#280000
0%
#285000
b101 ,
1%
#290000
0%
#295000
b110 ,
1%
#300000
0%
#305000
b111 ,
1%
#310000
0%
#315000
1#
1*
1!
11
b10 .
b111111101101110010111010100110000111011001010100001100100001 0
b0 ,
1%
#320000
0%
#325000
1#
1*
b1 ,
1%
#330000
0%
#335000
1#
1*
b10 ,
1%
#340000
0%
#345000
1#
1*
b11 ,
1%
#350000
0%
#355000
1#
1*
0!
01
b100 ,
1%
#360000
0%
#365000
1#
1*
b101 ,
1%
#370000
0%
#375000
1#
1*
b110 ,
1%
#380000
0%
#385000
1#
1*
b111 ,
1%
#390000
0%
#395000
0#
0*
1!
11
b11 .
b1111111011011100101110101001100001110110010101000011001000 0
b0 ,
1%
#400000
0%
#405000
b1 ,
1%
#410000
0%
#415000
b10 ,
1%
#420000
0%
#425000
b11 ,
1%
#430000
0%
#435000
0!
01
b100 ,
1%
#440000
0%
#445000
b101 ,
1%
#450000
0%
#455000
b110 ,
1%
#460000
0%
#465000
b111 ,
1%
#470000
0%
#475000
1"
1+
1!
11
b100 .
b11111110110111001011101010011000011101100101010000110010 0
b0 ,
1%
#480000
0%
#485000
1"
1+
b1 ,
1%
#490000
0%
#495000
1"
1+
b10 ,
1%
#500000
0%
#505000
1"
1+
b11 ,
1%
#510000
0%
#515000
1"
1+
0!
01
b100 ,
1%
#520000
0%
#525000
1"
1+
b101 ,
1%
#530000
0%
#535000
1"
1+
b110 ,
1%
#540000
0%
#545000
1"
1+
b111 ,
1%
#550000
0%
#555000
0"
0+
1!
11
b101 .
b111111101101110010111010100110000111011001010100001100 0
b0 ,
1%
#560000
0%
#565000
b1 ,
1%
#570000
0%
#575000
b10 ,
1%
#580000
0%
#585000
b11 ,
1%
#590000
0%
#595000
0!
01
b100 ,
1%
#600000
0%
#605000
b101 ,
1%
#610000
0%
#615000
b110 ,
1%
#620000
0%
#625000
b111 ,
1%
#630000
0%
#635000
1"
1+
1#
1*
1!
11
b110 .
b1111111011011100101110101001100001110110010101000011 0
b0 ,
1%
#640000
0%
#645000
1"
1+
1#
1*
b1 ,
1%
#650000
0%
#655000
1"
1+
1#
1*
b10 ,
1%
#660000
0%
#665000
1"
1+
1#
1*
b11 ,
1%
#670000
0%
#675000
1"
1+
1#
1*
0!
01
b100 ,
1%
#680000
0%
#685000
1"
1+
1#
1*
b101 ,
1%
#690000
0%
#695000
1"
1+
1#
1*
b110 ,
1%
#700000
0%
#705000
1"
1+
1#
1*
b111 ,
1%
#710000
0%
#715000
0"
0+
0#
0*
1!
11
b111 .
b11111110110111001011101010011000011101100101010000 0
b0 ,
1%
#720000
0%
#725000
b1 ,
1%
#730000
0%
#735000
b10 ,
1%
#740000
0%
#745000
b11 ,
1%
#750000
0%
#755000
0!
01
b100 ,
1%
#760000
0%
#765000
b101 ,
1%
#770000
0%
#775000
b110 ,
1%
#780000
0%
#785000
b111 ,
1%
#790000
0%
#795000
1!
11
b1000 .
b111111101101110010111010100110000111011001010100 0
b0 ,
1%
#800000
0%
#805000
b1 ,
1%
#810000
0%
#815000
b10 ,
1%
#820000
0%
#825000
b11 ,
1%
#830000
0%
#835000
0!
01
b100 ,
1%
#840000
0%
#845000
b101 ,
1%
#850000
0%
#855000
b110 ,
1%
#860000
0%
#865000
b111 ,
1%
#870000
0%
#875000
1#
1*
1!
11
b1001 .
b1111111011011100101110101001100001110110010101 0
b0 ,
1%
#880000
0%
#885000
1#
1*
b1 ,
1%
#890000
0%
#895000
1#
1*
b10 ,
1%
#900000
0%
#905000
1#
1*
b11 ,
1%
#910000
0%
#915000
1#
1*
0!
01
b100 ,
1%
#920000
0%
#925000
1#
1*
b101 ,
1%
#930000
0%
#935000
1#
1*
b110 ,
1%
#940000
0%
#945000
1#
1*
b111 ,
1%
#950000
0%
#955000
1#
1*
1!
11
b1010 .
b11111110110111001011101010011000011101100101 0
b0 ,
1%
#960000
0%
#965000
1#
1*
b1 ,
1%
#970000
0%
#975000
1#
1*
b10 ,
1%
#980000
0%
#985000
1#
1*
b11 ,
1%
#990000
0%
#995000
1#
1*
0!
01
b100 ,
1%
#1000000
0%
#1005000
1#
1*
b101 ,
1%
#1010000
0%
#1015000
1#
1*
b110 ,
1%
#1020000
0%
#1025000
1#
1*
b111 ,
1%
#1030000
0%
#1035000
1#
1*
1!
11
b1011 .
b111111101101110010111010100110000111011001 0
b0 ,
1%
#1040000
0%
#1045000
1#
1*
b1 ,
1%
#1050000
0%
#1055000
1#
1*
b10 ,
1%
#1060000
0%
#1065000
1#
1*
b11 ,
1%
#1070000
0%
#1075000
1#
1*
0!
01
b100 ,
1%
#1080000
0%
#1085000
1#
1*
b101 ,
1%
#1090000
0%
#1095000
1#
1*
b110 ,
1%
#1100000
0%
#1105000
1#
1*
b111 ,
1%
#1110000
0%
#1115000
1"
1+
0#
0*
1!
11
b1100 .
b1111111011011100101110101001100001110110 0
b0 ,
1%
#1120000
0%
#1125000
1"
1+
b1 ,
1%
#1130000
0%
#1135000
1"
1+
b10 ,
1%
#1140000
0%
#1145000
1"
1+
b11 ,
1%
#1150000
0%
#1155000
1"
1+
0!
01
b100 ,
1%
#1160000
0%
#1165000
1"
1+
b101 ,
1%
#1170000
0%
#1175000
1"
1+
b110 ,
1%
#1180000
0%
#1185000
1"
1+
b111 ,
1%
#1190000
0%
#1195000
1#
1*
0"
0+
1!
11
b1101 .
b11111110110111001011101010011000011101 0
b0 ,
1%
#1200000
0%
#1205000
1#
1*
b1 ,
1%
#1210000
0%
#1215000
1#
1*
b10 ,
1%
#1220000
0%
#1225000
1#
1*
b11 ,
1%
#1230000
0%
#1235000
1#
1*
0!
01
b100 ,
1%
#1240000
0%
#1245000
1#
1*
b101 ,
1%
#1250000
0%
#1255000
1#
1*
b110 ,
1%
#1260000
0%
#1265000
1#
1*
b111 ,
1%
#1270000
0%
#1275000
1"
1+
1#
1*
1!
11
b1110 .
b111111101101110010111010100110000111 0
b0 ,
1%
#1280000
0%
#1285000
1"
1+
1#
1*
b1 ,
1%
#1290000
0%
#1295000
1"
1+
1#
1*
b10 ,
1%
#1300000
0%
#1305000
1"
1+
1#
1*
b11 ,
1%
#1310000
0%
#1315000
1"
1+
1#
1*
0!
01
b100 ,
1%
#1320000
0%
#1325000
1"
1+
1#
1*
b101 ,
1%
#1330000
0%
#1335000
1"
1+
1#
1*
b110 ,
1%
#1340000
0%
#1345000
1"
1+
1#
1*
b111 ,
1%
#1350000
0%
#1355000
0"
0+
1#
1*
1!
11
b1111 .
b1111111011011100101110101001100001 0
b0 ,
1%
#1360000
0%
#1365000
1#
1*
b1 ,
1%
#1370000
0%
#1375000
1#
1*
b10 ,
1%
#1380000
0%
#1385000
1#
1*
b11 ,
1%
#1390000
0%
#1395000
1#
1*
0!
01
b100 ,
1%
#1400000
0%
#1405000
1#
1*
b101 ,
1%
#1410000
0%
#1415000
1#
1*
b110 ,
1%
#1420000
0%
#1425000
1#
1*
b111 ,
1%
#1430000
0%
#1435000
0#
0*
1!
11
b10000 .
b11111110110111001011101010011000 0
b0 ,
1%
#1440000
0%
#1445000
b1 ,
1%
#1450000
0%
#1455000
b10 ,
1%
#1460000
0%
#1465000
b11 ,
1%
#1470000
0%
#1475000
0!
01
b100 ,
1%
#1480000
0%
#1485000
b101 ,
1%
#1490000
0%
#1495000
b110 ,
1%
#1500000
0%
#1505000
b111 ,
1%
#1510000
0%
#1515000
1"
1+
1!
11
b10001 .
b111111101101110010111010100110 0
b0 ,
1%
#1520000
0%
#1525000
1"
1+
b1 ,
1%
#1530000
0%
#1535000
1"
1+
b10 ,
1%
#1540000
0%
#1545000
1"
1+
b11 ,
1%
#1550000
0%
#1555000
1"
1+
0!
01
b100 ,
1%
#1560000
0%
#1565000
1"
1+
b101 ,
1%
#1570000
0%
#1575000
1"
1+
b110 ,
1%
#1580000
0%
#1585000
1"
1+
b111 ,
1%
#1590000
0%
#1595000
1#
1*
0"
0+
1!
11
b10010 .
b1111111011011100101110101001 0
b0 ,
1%
#1600000
0%
#1605000
1#
1*
b1 ,
1%
#1610000
0%
#1615000
1#
1*
b10 ,
1%
#1620000
0%
#1625000
1#
1*
b11 ,
1%
#1630000
0%
#1635000
1#
1*
0!
01
b100 ,
1%
#1640000
0%
#1645000
1#
1*
b101 ,
1%
#1650000
0%
#1655000
1#
1*
b110 ,
1%
#1660000
0%
#1665000
1#
1*
b111 ,
1%
#1670000
0%
#1675000
1"
1+
0#
0*
1!
11
b10011 .
b11111110110111001011101010 0
b0 ,
1%
#1680000
0%
#1685000
1"
1+
b1 ,
1%
#1690000
0%
#1695000
1"
1+
b10 ,
1%
#1700000
0%
#1705000
1"
1+
b11 ,
1%
#1710000
0%
#1715000
1"
1+
0!
01
b100 ,
1%
#1720000
0%
#1725000
1"
1+
b101 ,
1%
#1730000
0%
#1735000
1"
1+
b110 ,
1%
#1740000
0%
#1745000
1"
1+
b111 ,
1%
#1750000
0%
#1755000
1"
1+
1!
11
b10100 .
b111111101101110010111010 0
b0 ,
1%
#1760000
0%
#1765000
1"
1+
b1 ,
1%
#1770000
0%
#1775000
1"
1+
b10 ,
1%
#1780000
0%
#1785000
1"
1+
b11 ,
1%
#1790000
0%
#1795000
1"
1+
0!
01
b100 ,
1%
#1800000
0%
#1805000
1"
1+
b101 ,
1%
#1810000
0%
#1815000
1"
1+
b110 ,
1%
#1820000
0%
#1825000
1"
1+
b111 ,
1%
#1830000
0%
#1835000
1"
1+
1!
11
b10101 .
b1111111011011100101110 0
b0 ,
1%
#1840000
0%
#1845000
1"
1+
b1 ,
1%
#1850000
0%
#1855000
1"
1+
b10 ,
1%
#1860000
0%
#1865000
1"
1+
b11 ,
1%
#1870000
0%
#1875000
1"
1+
0!
01
b100 ,
1%
#1880000
0%
#1885000
1"
1+
b101 ,
1%
#1890000
0%
#1895000
1"
1+
b110 ,
1%
#1900000
0%
#1905000
1"
1+
b111 ,
1%
#1910000
0%
#1915000
1#
1*
1"
1+
1!
11
b10110 .
b11111110110111001011 0
b0 ,
1%
#1920000
0%
#1925000
1"
1+
1#
1*
b1 ,
1%
#1930000
0%
#1935000
1"
1+
1#
1*
b10 ,
1%
#1940000
0%
#1945000
1"
1+
1#
1*
b11 ,
1%
#1950000
0%
#1955000
1"
1+
1#
1*
0!
01
b100 ,
1%
#1960000
0%
#1965000
1"
1+
1#
1*
b101 ,
1%
#1970000
0%
#1975000
1"
1+
1#
1*
b110 ,
1%
#1980000
0%
#1985000
1"
1+
1#
1*
b111 ,
1%
#1990000
0%
#1995000
1"
1+
0#
0*
1!
11
b10111 .
b111111101101110010 0
b0 ,
1%
#2000000
0%
#2005000
1"
1+
b1 ,
1%
#2010000
0%
#2015000
1"
1+
b10 ,
1%
#2020000
0%
#2025000
1"
1+
b11 ,
1%
#2030000
0%
#2035000
1"
1+
0!
01
b100 ,
1%
#2040000
0%
#2045000
1"
1+
b101 ,
1%
#2050000
0%
#2055000
1"
1+
b110 ,
1%
#2060000
0%
#2065000
1"
1+
b111 ,
1%
#2070000
0%
#2075000
0"
0+
1!
11
b11000 .
b1111111011011100 0
b0 ,
1%
#2080000
0%
#2085000
b1 ,
1%
#2090000
0%
#2095000
b10 ,
1%
#2100000
0%
#2105000
b11 ,
1%
#2110000
0%
#2115000
0!
01
b100 ,
1%
#2120000
0%
#2125000
b101 ,
1%
#2130000
0%
#2135000
b110 ,
1%
#2140000
0%
#2145000
b111 ,
1%
#2150000
0%
#2155000
1"
1+
1#
1*
1!
11
b11001 .
b11111110110111 0
b0 ,
1%
#2160000
0%
#2165000
1"
1+
1#
1*
b1 ,
1%
#2170000
0%
#2175000
1"
1+
1#
1*
b10 ,
1%
#2180000
0%
#2185000
1"
1+
1#
1*
b11 ,
1%
#2190000
0%
#2195000
1"
1+
1#
1*
0!
01
b100 ,
1%
#2200000
0%
#2205000
1"
1+
1#
1*
b101 ,
1%
#2210000
0%
#2215000
1"
1+
1#
1*
b110 ,
1%
#2220000
0%
#2225000
1"
1+
1#
1*
b111 ,
1%
#2230000
0%
#2235000
0"
0+
1#
1*
1!
11
b11010 .
b111111101101 0
b0 ,
1%
#2240000
0%
#2245000
1#
1*
b1 ,
1%
#2250000
0%
#2255000
1#
1*
b10 ,
1%
#2260000
0%
#2265000
1#
1*
b11 ,
1%
#2270000
0%
#2275000
1#
1*
0!
01
b100 ,
1%
#2280000
0%
#2285000
1#
1*
b101 ,
1%
#2290000
0%
#2295000
1#
1*
b110 ,
1%
#2300000
0%
#2305000
1#
1*
b111 ,
1%
#2310000
0%
#2315000
1"
1+
1#
1*
1!
11
b11011 .
b1111111011 0
b0 ,
1%
#2320000
0%
#2325000
1"
1+
1#
1*
b1 ,
1%
#2330000
0%
#2335000
1"
1+
1#
1*
b10 ,
1%
#2340000
0%
#2345000
1"
1+
1#
1*
b11 ,
1%
#2350000
0%
#2355000
1"
1+
1#
1*
0!
01
b100 ,
1%
#2360000
0%
#2365000
1"
1+
1#
1*
b101 ,
1%
#2370000
0%
#2375000
1"
1+
1#
1*
b110 ,
1%
#2380000
0%
#2385000
1"
1+
1#
1*
b111 ,
1%
#2390000
0%
#2395000
1"
1+
0#
0*
1!
11
b11100 .
b11111110 0
b0 ,
1%
#2400000
0%
#2405000
1"
1+
b1 ,
1%
#2410000
0%
#2415000
1"
1+
b10 ,
1%
#2420000
0%
#2425000
1"
1+
b11 ,
1%
#2430000
0%
#2435000
1"
1+
0!
01
b100 ,
1%
#2440000
0%
#2445000
1"
1+
b101 ,
1%
#2450000
0%
#2455000
1"
1+
b110 ,
1%
#2460000
0%
#2465000
1"
1+
b111 ,
1%
#2470000
0%
#2475000
1#
1*
1"
1+
1!
11
b11101 .
b111111 0
b0 ,
1%
#2480000
0%
#2485000
1"
1+
1#
1*
b1 ,
1%
#2490000
0%
#2495000
1"
1+
1#
1*
b10 ,
1%
#2500000
0%
#2505000
1"
1+
1#
1*
b11 ,
1%
#2510000
0%
#2515000
1"
1+
1#
1*
0!
01
b100 ,
1%
#2520000
0%
#2525000
1"
1+
1#
1*
b101 ,
1%
#2530000
0%
#2535000
1"
1+
1#
1*
b110 ,
1%
#2540000
0%
#2545000
1"
1+
1#
1*
b111 ,
1%
#2550000
0%
#2555000
1"
1+
1#
1*
1!
11
b11110 .
b1111 0
b0 ,
1%
#2560000
0%
#2565000
1"
1+
1#
1*
b1 ,
1%
#2570000
0%
#2575000
1"
1+
1#
1*
b10 ,
1%
#2580000
0%
#2585000
1"
1+
1#
1*
b11 ,
1%
#2590000
0%
#2595000
1"
1+
1#
1*
0!
01
b100 ,
1%
#2600000
0%
#2605000
1"
1+
1#
1*
b101 ,
1%
#2610000
0%
#2615000
1"
1+
1#
1*
b110 ,
1%
#2620000
0%
#2625000
1"
1+
1#
1*
b111 ,
1%
#2630000
0%
#2635000
1"
1+
1#
1*
1!
11
b11111 .
b11 0
b0 ,
1%
#2640000
0%
#2645000
1"
1+
1#
1*
b1 ,
1%
#2650000
0%
#2655000
1"
1+
1#
1*
b10 ,
1%
#2660000
0%
#2665000
1"
1+
1#
1*
b11 ,
1%
#2670000
0%
#2675000
1"
1+
1#
1*
0!
01
b100 ,
1%
#2680000
0%
#2685000
1"
1+
1#
1*
b101 ,
1%
#2690000
0%
#2695000
1"
1+
1#
1*
b110 ,
1%
#2700000
0%
#2705000
b11 /
1"
1+
1#
1*
b111 ,
1%
#2710000
0%
#2715000
0"
0+
0#
0*
b11 2
1!
11
b0 0
b0 ,
1%
#2720000
0%
#2725000
b1 ,
b0 -
b0 .
1%
#2730000
0%
#2735000
b10 ,
1%
#2740000
0%
#2745000
b11 ,
1%
#2750000
0%
#2755000
0!
01
b100 ,
1%
#2760000
0%
#2765000
b101 ,
1%
#2770000
0%
#2775000
b110 ,
1%
#2780000
0%
#2785000
b0 /
b111 ,
1%
#2790000
0%
#2795000
b0 2
b0 ,
1%
